tilde/__init__.py
tilde/cli.py
tilde/config.py
tilde/schema.py
tilde/server.py
tilde/storage.py
tilde/updates.py
tilde/ingest/__init__.py
tilde/ingest/extractor.py
tilde/ingest/loader.py
tilde/ingest/resume_extractor.py
tilde/ingest/skill_extractor.py
tilde/team/__init__.py
tilde/team/manager.py
tilde/team/sync.py
tilde_ai-0.1.0.dist-info/METADATA
tilde_ai-0.1.0.dist-info/WHEEL
tilde_ai-0.1.0.dist-info/entry_points.txt
tilde_ai-0.1.0.dist-info/RECORD
