Metadata-Version: 2.4
Name: tilde-ai
Version: 0.1.0
Summary: Your AI agents' home directory — privacy-first MCP server for portable AI identity
Project-URL: Homepage, https://github.com/topskychen/tilde
Project-URL: Repository, https://github.com/topskychen/tilde
Project-URL: Issues, https://github.com/topskychen/tilde/issues
Author: Qian Chen
License: MIT
Keywords: ai-agents,claude,cursor,llm,mcp,model-context-protocol,privacy-first,profile
Classifier: Development Status :: 4 - Beta
Classifier: Intended Audience :: Developers
Classifier: License :: OSI Approved :: MIT License
Classifier: Programming Language :: Python :: 3
Classifier: Programming Language :: Python :: 3.11
Classifier: Programming Language :: Python :: 3.12
Classifier: Topic :: Scientific/Engineering :: Artificial Intelligence
Classifier: Topic :: Software Development :: Libraries :: Python Modules
Requires-Python: >=3.11
Requires-Dist: google-genai>=1.57.0
Requires-Dist: mcp>=1.0.0
Requires-Dist: pydantic>=2.0.0
Requires-Dist: pyyaml>=6.0.0
Requires-Dist: rich>=13.0.0
Requires-Dist: typer>=0.12.0
